DashAI/__init__.py
DashAI/__main__.py
DashAI/runner.py
DashAI/back/__init__.py
DashAI/back/app.py
DashAI/back/config.py
DashAI/back/config_object.py
DashAI/back/container.py
DashAI/back/initial_components.py
DashAI/back/api/__init__.py
DashAI/back/api/front_api.py
DashAI/back/api/utils.py
DashAI/back/api/api_v0/__init__.py
DashAI/back/api/api_v0/api.py
DashAI/back/api/api_v0/endpoints/__init__.py
DashAI/back/api/api_v0/endpoints/old_endpoints.py
DashAI/back/api/api_v0/endpoints/session_class.py
DashAI/back/api/api_v1/__init__.py
DashAI/back/api/api_v1/api.py
DashAI/back/api/api_v1/endpoints/__init__.py
DashAI/back/api/api_v1/endpoints/components.py
DashAI/back/api/api_v1/endpoints/converters.py
DashAI/back/api/api_v1/endpoints/datasets.py
DashAI/back/api/api_v1/endpoints/experiments.py
DashAI/back/api/api_v1/endpoints/explainers.py
DashAI/back/api/api_v1/endpoints/explorers.py
DashAI/back/api/api_v1/endpoints/generative_process.py
DashAI/back/api/api_v1/endpoints/generative_session.py
DashAI/back/api/api_v1/endpoints/jobs.py
DashAI/back/api/api_v1/endpoints/notebook.py
DashAI/back/api/api_v1/endpoints/pipelines.py
DashAI/back/api/api_v1/endpoints/plugins.py
DashAI/back/api/api_v1/endpoints/predict.py
DashAI/back/api/api_v1/endpoints/runs.py
DashAI/back/api/api_v1/schemas/__init__.py
DashAI/back/api/api_v1/schemas/converter_params.py
DashAI/back/api/api_v1/schemas/datasets_params.py
DashAI/back/api/api_v1/schemas/experiments_params.py
DashAI/back/api/api_v1/schemas/explainers_params.py
DashAI/back/api/api_v1/schemas/exploration_params.py
DashAI/back/api/api_v1/schemas/explorers_params.py
DashAI/back/api/api_v1/schemas/generative_process_params.py
DashAI/back/api/api_v1/schemas/generative_session_params.py
DashAI/back/api/api_v1/schemas/generative_session_params_history.py
DashAI/back/api/api_v1/schemas/job_params.py
DashAI/back/api/api_v1/schemas/notebook_params.py
DashAI/back/api/api_v1/schemas/pipelines_params.py
DashAI/back/api/api_v1/schemas/plugin_params.py
dashai-0.3.0.dist-info/METADATA
dashai-0.3.0.dist-info/WHEEL
dashai-0.3.0.dist-info/entry_points.txt
dashai-0.3.0.dist-info/top_level.txt
dashai-0.3.0.dist-info/RECORD
