Metadata-Version: 2.4
Name: DashAI
Version: 0.3.0
Summary: DashAI: a graphical toolbox for training, evaluating and deploying state-of-the-art AI models.
Home-page: https://github.com/DashAISoftware/DashAI
Author: DashAI Team
Author-email: fbravo@dcc.uchile.cl
License: MIT
Project-URL: Documentation, https://dash-ai.com/
Project-URL: Changelog, https://dash-ai.com/changelog.html
Project-URL: Issue Tracker, https://github.com/DashAISoftware/DashAI/issues
Classifier: Programming Language :: Python :: 3.10
Classifier: Programming Language :: Python :: 3.11
Classifier: License :: OSI Approved :: MIT License
Classifier: Operating System :: OS Independent
Requires-Python: >=3.10
Requires-Dist: fastapi[all]
Requires-Dist: SQLAlchemy
Requires-Dist: streaming_form_data
Requires-Dist: alembic
Requires-Dist: kink
Requires-Dist: numpy
Requires-Dist: pandas
Requires-Dist: joblib
Requires-Dist: pydantic
Requires-Dist: pydantic-settings
Requires-Dist: starlette
Requires-Dist: scikit-learn
Requires-Dist: datasets
Requires-Dist: diffusers
Requires-Dist: evaluate
Requires-Dist: accelerate
Requires-Dist: Pillow
Requires-Dist: beartype
Requires-Dist: plotly
Requires-Dist: shap
Requires-Dist: typer
Requires-Dist: rich
Requires-Dist: torch
Requires-Dist: torchvision
Requires-Dist: transformers
Requires-Dist: sacrebleu
Requires-Dist: sentencepiece
Requires-Dist: optuna
Requires-Dist: hyperopt
Requires-Dist: openpyxl
Requires-Dist: httpx
Requires-Dist: wordcloud
Requires-Dist: opencv-python
Requires-Dist: protobuf
Requires-Dist: imblearn
Requires-Dist: numba
Requires-Dist: llvmlite
Requires-Dist: huey
Requires-Dist: xlrd
Dynamic: author
Dynamic: author-email
Dynamic: classifier
Dynamic: description
Dynamic: home-page
Dynamic: license
Dynamic: project-url
Dynamic: requires-dist
Dynamic: requires-python
Dynamic: summary
